{
  "project_info": {
    "project_number": "366469491229",
    "project_id": "lastuplaodphoto",
    "storage_bucket": "lastuplaodphoto.appspot.com"
  },
  "client": [
    {
      "client_info": {
        "mobilesdk_app_id": "1:366469491229:android:34865fb713df40aab234f4",
        "android_client_info": {
          "package_name": "com.example.storageexample"
        }
      },
      "oauth_client": [
        {
          "client_id": "366469491229-19u2oefvk5u33ff0otq65u86o49nqptt.apps.googleusercontent.com",
          "client_type": 3
        }
      ],
      "api_key": [
        {
          "current_key": "AIzaSyCZMODaOa3dyZ0EiGK7pMlN9n05aPQKoJQ"
        }
      ],
      "services": {
        "appinvite_service": {
          "other_platform_oauth_client": [
            {
              "client_id": "366469491229-19u2oefvk5u33ff0otq65u86o49nqptt.apps.googleusercontent.com",
              "client_type": 3
            }
          ]
        }
      }
    }
  ],
  "configuration_version": "1"
}